COPYING.txt
MANIFEST.in
README.md
setup.py
examples/example1.py
examples/test_data1/test1.cfg
examples/test_data1/test1.dat
examples/test_data1/test1.inf
examples/test_data2/test2.cfg
examples/test_data2/test2.dat
examples/test_data2/test2.inf
examples/test_data3/test3.cfg
examples/test_data3/test3.dat
examples/test_data3/test3.inf
examples/test_data3/test3_ascii.cfg
examples/test_data3/test3_ascii.dat
examples/test_data3/test3_ascii.inf
pyComtrade.egg-info/PKG-INFO
pyComtrade.egg-info/SOURCES.txt
pyComtrade.egg-info/dependency_links.txt
pyComtrade.egg-info/requires.txt
pyComtrade.egg-info/top_level.txt
src/__init__.py
src/pyComtrade.py
src/utils.py