Metadata-Version: 1.2
Name: pyComtrade
Version: 0.3.1
Summary: Python module for reading Comtrade files.
Home-page: https://github.com/miguelmoreto/pycomtrade
Author: Miguel Moreto
Author-email: miguel.moreto@ufsc.br
Maintainer: Miguel Moreto
Maintainer-email: miguel.moreto@ufsc.br
License: GPLv3
Platform: UNKNOWN
